trossen_arm-1.8.8.dist-info/RECORD
trossen_arm-1.8.8.dist-info/WHEEL
trossen_arm-1.8.8.dist-info/METADATA
trossen_arm-1.8.8.dist-info/licenses/LICENSE-3RD-PARTY.txt
trossen_arm-1.8.8.dist-info/licenses/LICENSE
trossen_arm/trossen_arm.pyi
trossen_arm/trossen_arm.cpython-312-aarch64-linux-gnu.so
trossen_arm/__init__.py
